click_inspect/__init__.py
click_inspect/decorators.py
click_inspect/errors.py
click_inspect/parser.py
click_inspect-0.3.2.dist-info/LICENSE
click_inspect-0.3.2.dist-info/WHEEL
click_inspect-0.3.2.dist-info/METADATA
click_inspect-0.3.2.dist-info/RECORD
