Metadata-Version: 2.1
Name: click-inspect
Version: 0.3.2
Summary: Add options to click commands based on inspecting functions
Home-page: https://github.com/Dominik1123/click-inspect
License: MIT
Keywords: click,command line interface,inspect
Author: Dominik1123
Requires-Python: >=3.7.9,<4.0.0
Classifier: License :: OSI Approved :: MIT License
Classifier: Programming Language :: Python :: 3
Classifier: Programming Language :: Python :: 3.8
Requires-Dist: Sphinx (>=3.3.0,<4.0.0)
Requires-Dist: click (>=7.1.2,<8.0.0)
Requires-Dist: importlib_metadata (>=1.6.1,<2.0.0); python_version < "3.8"
Requires-Dist: typestring-parser (>=0.1,<0.2)
Requires-Dist: typing-extensions (>=3.7.4.3,<4.0.0.0); python_version < "3.9"
Project-URL: Repository, https://github.com/Dominik1123/click-inspect
